CHANGELOG.md
aeternity/__init__.py
aeternity/__main__.py
aeternity/aens.py
aeternity/channel.py
aeternity/compiler.py
aeternity/contract.py
aeternity/contract_native.py
aeternity/defaults.py
aeternity/exceptions.py
aeternity/hashing.py
aeternity/hdwallet.py
aeternity/identifiers.py
aeternity/node.py
aeternity/openapi.py
aeternity/oracles.py
aeternity/signing.py
aeternity/transactions.py
aeternity/utils.py
aepp_sdk-7.0.0.dist-info/entry_points.txt
aepp_sdk-7.0.0.dist-info/LICENSE.txt
aepp_sdk-7.0.0.dist-info/WHEEL
aepp_sdk-7.0.0.dist-info/METADATA
aepp_sdk-7.0.0.dist-info/RECORD
