Metadata-Version: 2.1
Name: aepp-sdk
Version: 7.0.0
Summary: Python SDK to interact with the Æternity blockchain
Home-page: https://github.com/aeternity/aepp-sdk-python
License: ISC
Keywords: aeternity,blockchain,sdk
Author: Andrea Giacobino
Author-email: no.andrea@gmail.com
Requires-Python: >=3.7,<4.0
Classifier: Intended Audience :: Developers
Classifier: License :: OSI Approved
Classifier: License :: OSI Approved :: ISC License (ISCL)
Classifier: Operating System :: OS Independent
Classifier: Programming Language :: Python :: 3
Classifier: Programming Language :: Python :: 3.7
Classifier: Programming Language :: Python :: 3.8
Provides-Extra: test
Requires-Dist: Deprecated (>=1.2,<2.0)
Requires-Dist: PyNaCl (>=1.3,<2.0)
Requires-Dist: base58 (>=1,<3)
Requires-Dist: click (>=7.0,<8.0)
Requires-Dist: mnemonic (>=0.19.0,<0.20.0)
Requires-Dist: munch (>=2.5,<3.0)
Requires-Dist: requests (>=2.20,<3.0)
Requires-Dist: rlp (>=1.1,<2.0)
Requires-Dist: semver (>=2.8,<3.0)
Requires-Dist: simplejson (>=3.16.0,<4.0.0)
Requires-Dist: validators (>=0.13,<0.15)
Requires-Dist: websockets (>=7,<9)
Project-URL: Repository, https://github.com/aeternity/aepp-sdk-python
